{"0":"Why you actin' all","1":"Shy and all","2":"Why is y'all","3":"Lyin' for?","4":"\"I never did this before...\"","5":"Stop that","6":"What, you want some Patron?","7":"I got that","8":"I mean I promise y'all","9":"You fine and all","10":"And your girlfriend, she kinda raw","11":"But she not like you","12":"No, she not like you","13":"Right now I need you to mute all the monologue","14":"All that talking is gon' give me a Tylenol","15":"You put a nigga to sleep, I'm tired of y'all","16":"Right now the Louis Vuitton don is signing off","17":"See you know my style","18":"I'm very wild","19":"And I vow that my child will be well endowed","20":"Like his daddy","21":"And tell him that your mama had a fattie","22":"He looked up at me said, \"daddy that's the reason why you had me?\"","23":"Yep, we was praticing","24":"Til one day your ass bust through the packaging","25":"You know what though? You my favorite accident","26":"So go head pop some Cristal","27":"For my newborn child","28":" cuz now y'all","title":"Celebration","artist":"Kanye West","album":"Late Registration","feature":false}